chaste_codegen/__init__.py
chaste_codegen/_chaste_printer.py
chaste_codegen/_command_line_script.py
chaste_codegen/_config.py
chaste_codegen/_jacobian.py
chaste_codegen/_labview_printer.py
chaste_codegen/_linearity_check.py
chaste_codegen/_load_template.py
chaste_codegen/_lookup_tables.py
chaste_codegen/_math_functions.py
chaste_codegen/_optimize.py
chaste_codegen/_partial_eval.py
chaste_codegen/_rdf.py
chaste_codegen/_script_utils.py
chaste_codegen/backward_euler_model.py
chaste_codegen/backward_euler_opt_model.py
chaste_codegen/chaste_model.py
chaste_codegen/cvode_chaste_model.py
chaste_codegen/cvode_opt_chaste_model.py
chaste_codegen/generalised_rush_larsen_1_model.py
chaste_codegen/generalised_rush_larsen_1_opt_model.py
chaste_codegen/generalised_rush_larsen_2_model.py
chaste_codegen/generalised_rush_larsen_2_opt_model.py
chaste_codegen/model_with_conversions.py
chaste_codegen/normal_chaste_model.py
chaste_codegen/opt_chaste_model.py
chaste_codegen/rush_larsen_c.py
chaste_codegen/rush_larsen_labview.py
chaste_codegen/rush_larsen_model.py
chaste_codegen/rush_larsen_opt_model.py
chaste_codegen/version.txt
chaste_codegen/ontologies/.git
chaste_codegen/ontologies/LICENSE
chaste_codegen/ontologies/README.md
chaste_codegen/ontologies/oxford-metadata.rdf
chaste_codegen/ontologies/oxford-metadata.ttl
chaste_codegen/ontologies/ttl2rdf.py
chaste_codegen/templates/backward_euler_model.cpp
chaste_codegen/templates/backward_euler_model.hpp
chaste_codegen/templates/cvode_model.cpp
chaste_codegen/templates/cvode_model.hpp
chaste_codegen/templates/generalised_rush_larsen_model.hpp
chaste_codegen/templates/generalised_rush_larsen_model_1.cpp
chaste_codegen/templates/generalised_rush_larsen_model_2.cpp
chaste_codegen/templates/hello.txt
chaste_codegen/templates/labview.c
chaste_codegen/templates/labview.h
chaste_codegen/templates/labview.txt
chaste_codegen/templates/normal_model.cpp
chaste_codegen/templates/normal_model.hpp
chaste_codegen/templates/rush_larsen_model.cpp
chaste_codegen-0.10.5.dist-info/LICENSE
chaste_codegen-0.10.5.dist-info/METADATA
chaste_codegen-0.10.5.dist-info/WHEEL
chaste_codegen-0.10.5.dist-info/entry_points.txt
chaste_codegen-0.10.5.dist-info/top_level.txt
chaste_codegen-0.10.5.dist-info/RECORD
