Metadata-Version: 2.1
Name: chaste_codegen
Version: 0.10.5
Summary: Code generation for cardiac Chaste
Home-page: https://github.com/ModellingWebLab/chaste-codegen
Author: Maurice Hendrix, Michael Clerx, Jonathan Cooper
Author-email: Maurice.Hendrix@nottingham.ac.uk
Maintainer: Maurice Hendrix
Maintainer-email: Maurice.Hendrix@nottingham.ac.uk
Classifier: Programming Language :: Python :: 3
Classifier: License :: OSI Approved :: BSD License
Classifier: Operating System :: OS Independent
Requires-Python: >=3.6
License-File: LICENSE
Requires-Dist: py >=1.10.0
Requires-Dist: decorator <6,>=4.4.2
Requires-Dist: importlib-metadata <8,>=1.7
Requires-Dist: isodate <1,>=0.6.0
Requires-Dist: lxml <6,>=4.6.5
Requires-Dist: MarkupSafe <3,>=1.1.1
Requires-Dist: mpmath <2,>=1.1.0
Requires-Dist: networkx <4,>=2.4
Requires-Dist: packaging <24,>=20.4
Requires-Dist: Pint <0.30,>=0.9
Requires-Dist: pyparsing <4,>=2.4.7
Requires-Dist: rdflib <8,>=5.0.0
Requires-Dist: six <2,>=1.15.0
Requires-Dist: sympy <1.11,>=1.9
Requires-Dist: zipp <4,>=1.2.0
Requires-Dist: Jinja2 <4,>=3.0.0
Requires-Dist: cellmlmanip <0.4,>=0.3.6
Provides-Extra: docs
Requires-Dist: sphinx >=3.0 ; extra == 'docs'
Requires-Dist: sphinx-automodapi >=0.12 ; extra == 'docs'
Provides-Extra: test
Requires-Dist: pytest-cov >=2.10 ; extra == 'test'
Requires-Dist: pytest >=4.6 ; extra == 'test'
Requires-Dist: flake8 >=3 ; extra == 'test'
Requires-Dist: isort ; extra == 'test'
Requires-Dist: mock >=3.0.5 ; extra == 'test'
